oss_lifecycle/__init__.py
oss_lifecycle/activity_report.py
oss_lifecycle/collector_script.py
oss_lifecycle/count_tokens.py
oss_lifecycle/fit_bass.py
oss_lifecycle/fit_innovation.py
oss_lifecycle/github_gather.py
oss_lifecycle/github_gather_old.py
oss_lifecycle/index.html
oss_lifecycle/script.js
oss_lifecycle/server.py
oss_lifecycle/stats.py
oss_lifecycle/styles.css
oss_lifecycle-0.1.3.dist-info/METADATA
oss_lifecycle-0.1.3.dist-info/WHEEL
oss_lifecycle-0.1.3.dist-info/licenses/LICENSE
oss_lifecycle-0.1.3.dist-info/RECORD
