Metadata-Version: 2.4
Name: oss-lifecycle
Version: 0.1.3
Summary: A package to analyze open-source GitHub projects life cycles
Project-URL: Homepage, https://github.com/srdas/oss-lifecycle/tree/main
Author-email: Sanjiv Das <srdas@scu.edu>
License: Copyright (c) 2025 Sanjiv Das
License-File: LICENSE
Classifier: Operating System :: OS Independent
Classifier: Programming Language :: Python :: 3
Requires-Python: >=3.12
Requires-Dist: flask
Requires-Dist: flask-cors
Requires-Dist: gitpython
Requires-Dist: matplotlib
Requires-Dist: numpy
Requires-Dist: pandas
Requires-Dist: scikit-learn
Requires-Dist: scipy
